CustomerProfile/CustomerProfile.py
CustomerProfile/__init__.py
CustomerProfile/utils.py
CustomerProfile/Data/__init__.py
CustomerProfile/Preprocessing/__init__.py
CustomerProfile/Preprocessing/outlier.py
CustomerProfile/Preprocessing/scaler.py
CustomerProfile/Report/__init__.py
CustomerProfile-0.1.0.dist-info/AUTHORS.rst
CustomerProfile-0.1.0.dist-info/LICENSE
CustomerProfile-0.1.0.dist-info/METADATA
CustomerProfile-0.1.0.dist-info/WHEEL
CustomerProfile-0.1.0.dist-info/top_level.txt
CustomerProfile-0.1.0.dist-info/RECORD
