Metadata-Version: 2.1
Name: CustomerProfile
Version: 0.1.0
Summary: An easy-to-use package for customer profile creation in Python.
Home-page: https://github.com/HrayrMuradyan/CustomerProfile
Author: Hrayr Muradyan
Author-email: hrayrmuradyan20@gmail.com
License: MIT license
Keywords: CustomerProfile
Classifier: Development Status :: 2 - Pre-Alpha
Classifier: Intended Audience :: Developers
Classifier: License :: OSI Approved :: MIT License
Classifier: Natural Language :: English
Classifier: Programming Language :: Python :: 3
Classifier: Programming Language :: Python :: 3.6
Classifier: Programming Language :: Python :: 3.7
Classifier: Programming Language :: Python :: 3.8
Requires-Python: >=3.6
License-File: LICENSE
License-File: AUTHORS.rst
